napari_mrcfile_reader/__init__.py
napari_mrcfile_reader/_reader.py
napari_mrcfile_reader/_version.py
napari_mrcfile_reader/napari.yaml
napari_mrcfile_reader/_tests/test_reader.py
napari_mrcfile_reader-0.2.0.dist-info/LICENSE
napari_mrcfile_reader-0.2.0.dist-info/METADATA
napari_mrcfile_reader-0.2.0.dist-info/WHEEL
napari_mrcfile_reader-0.2.0.dist-info/entry_points.txt
napari_mrcfile_reader-0.2.0.dist-info/top_level.txt
napari_mrcfile_reader-0.2.0.dist-info/RECORD
