Metadata-Version: 2.1
Name: napari-mrcfile-reader
Version: 0.2.0
Summary: Read MRC2014 files in napari using mrcfile.
Home-page: https://github.com/alisterburt/napari-mrcfile-reader
Author: Alister Burt
Author-email: alisterburt@gmail.com
License: BSD-3-Clause
Project-URL: Bug Tracker, https://github.com/alisterburt/napari-mrcfile-reader/issues
Project-URL: Documentation, https://github.com/alisterburt/napari-mrcfile-reader#README.md
Project-URL: Source Code, https://github.com/alisterburt/napari-mrcfile-reader
Project-URL: User Support, https://github.com/alisterburt/napari-mrcfile-reader/issues
Classifier: Development Status :: 2 - Pre-Alpha
Classifier: Framework :: napari
Classifier: Intended Audience :: Developers
Classifier: License :: OSI Approved :: BSD License
Classifier: Operating System :: OS Independent
Classifier: Programming Language :: Python
Classifier: Programming Language :: Python :: 3
Classifier: Programming Language :: Python :: 3 :: Only
Classifier: Programming Language :: Python :: 3.8
Classifier: Programming Language :: Python :: 3.9
Classifier: Programming Language :: Python :: 3.10
Classifier: Topic :: Scientific/Engineering :: Image Processing
Requires-Python: >=3.8
License-File: LICENSE
Requires-Dist: numpy
Requires-Dist: mrcfile
Provides-Extra: testing
Requires-Dist: tox ; extra == 'testing'
Requires-Dist: pytest ; extra == 'testing'
Requires-Dist: pytest-cov ; extra == 'testing'
